[
    {
      "id": 1,
      "name": "Project One",
      "description": "A web application built using React and Node.js.",
      "link": "https://y22-sdp10-automobilemanagementsystem.netlify.app/store"
      
    },
    {
      "id": 2,
      "name": "Project Two",
      "description": "Develop an application to implement multi-linear regression on a house price prediction dataset.",
      "link": "https://github.com/AsadiSaiBhavyaReddy/House_Price_Prediction-"
     
    },
    {
      "id": 3,
      "name": "Project Three",
      "description": "A web application built using React,Node.js and API's.",
      "link": "https://github.com/AsadiSaiBhavyaReddy/PRODIGY_WD_05"
     
    },
    {
      "id": 4,
      "name": "Project Four",
      "description": "This is a web application built using Visual Studio Code (VS Code), HTML, CSS, and JavaScript.",
      "link": "https://github.com/AsadiSaiBhavyaReddy/PRODIGY_WD_01"
    }

  ]
  